counter3.v
module counter3 (
    input  wire clk,
    input  wire reset,
    input  wire data,
    output reg  start_shifting
);

    localparam S0 = 3'd0;
    localparam S1 = 3'd1;
    localparam S2 = 3'd2;
    localparam S3 = 3'd3;
    localparam S4 = 3'd4;

    reg [2:0] state, next_state;

    always @(posedge clk) begin
        if (reset) begin
            state <= S0;
            start_shifting <= 1'b0;
        end else begin
            state <= next_state;
            if (next_state == S4) begin
                start_shifting <= 1'b1;
                state <= S0;
            end
        end
    end

    always @(*) begin
        case (state)
            S0: begin
                if (data == 1'b1) next_state = S1;
                else              next_state = S0;
            end
            S1: begin
                if (data == 1'b1) next_state = S2;
                else              next_state = S0;
            end
            S2: begin
                if (data == 1'b0) next_state = S3;
                else              next_state = S2;
            end
            S3: begin
                if (data == 1'b1) next_state = S4;
                else              next_state = S0;
            end
            S4: begin
                next_state = S4;
            end
            default: next_state = S0;
        endcase
    end

endmodule

counter3_tb.v
`timescale 1ns/1ps

module counter3_tb;
    reg clk = 0;
    reg reset = 1;
    reg data = 0;
    wire start_shifting;

    counter3 dut (
        .clk(clk),
        .reset(reset),
        .data(data),
        .start_shifting(start_shifting)
    );

    always #5 clk = ~clk;

    initial begin
        $dumpfile("counter3_tb.vcd");
        $dumpvars(0, counter3_tb);
    end

    task send_bit(input bit bitval);
        begin
            data <= bitval;
            @(posedge clk);
        end
    endtask

    initial begin
        $display("Starting counter3_tb");

        // release reset
        repeat (2) @(posedge clk);
        reset <= 0;

        // noise bits that should not trigger 1101
        send_bit(1'b0);
        send_bit(1'b0);
        if (start_shifting !== 1'b0) $fatal(1, "start_shifting asserted early");

        // apply pattern 1 1 0 1 (pulse start_shifting high)
        send_bit(1'b1);
        send_bit(1'b1);
        send_bit(1'b0);
        send_bit(1'b1);
        @(negedge clk);
        if (start_shifting !== 1'b1) $fatal(1, "start_shifting did not assert on 1101");

        // keep high while reset low, then clear on reset pulse
        send_bit(1'b1);
        send_bit(1'b1);
        if (start_shifting !== 1'b1) $fatal(1, "start_shifting deasserted unexpectedly");

        reset <= 1;
        @(posedge clk);
        reset <= 0;
        @(negedge clk);
        if (start_shifting !== 1'b0) $fatal(1, "start_shifting not cleared by reset");

        $display("counter3_tb passed");
        $finish;
    end
endmodule

counter3_tb.vcd
$date
	Tue Dec 02 18:51:24 2025
$end
$version
	Icarus Verilog
$end
$timescale
	1ps
$end
$scope module counter3_tb $end
$var wire 1 ! start_shifting $end
$var reg 1 " clk $end
$var reg 1 # data $end
$var reg 1 $ reset $end
$scope module dut $end
$var wire 1 " clk $end
$var wire 1 # data $end
$var wire 1 $ reset $end
$var parameter 3 % S0 $end
$var parameter 3 & S1 $end
$var parameter 3 ' S2 $end
$var parameter 3 ( S3 $end
$var parameter 3 ) S4 $end
$var reg 3 * next_state [2:0] $end
$var reg 1 ! start_shifting $end
$var reg 3 + state [2:0] $end
$upscope $end
$scope task send_bit $end
$var reg 1 , bitval $end
$upscope $end
$upscope $end
$enddefinitions $end
$comment Show the parameter values. $end
$dumpall
b100 )
b11 (
b10 '
b1 &
b0 %
$end
#0
$dumpvars
0,
bx +
bx *
1$
0#
0"
x!
$end
#5000
b0 *
0!
b0 +
1"
#10000
0"
#15000
0$
1"
#20000
0"
#25000
1"
#30000
0"
#35000
b1 *
1#
1,
1"
#40000
0"
#45000
b10 *
b1 +
1"
#50000
0"
#55000
b11 *
0#
b10 +
0,
1"
#60000
0"
#65000
b100 *
1#
b11 +
1,
1"
#70000
0"
#75000
b1 *
1!
b0 +
1"
#80000
0"
#85000
b10 *
b1 +
1"
#90000
0"
#95000
1$
b10 +
1"
#100000
0"
#105000
b1 *
0!
b0 +
0$
1"
