counter2.v
module counter2 (
    input  wire       clk,        
    input  wire       shift_ena, 
    input  wire       count_ena,  
    input  wire       data,
    input  wire       reset, 
    output reg  [3:0] q          
);
    always @(posedge clk) begin
        if (reset) q <= 4'd0;
        if (shift_ena) begin
            q <= {q[2:0], data};
        end
        if (count_ena) begin
            q <= q - 1;
        end
    end

endmodule

counter2_tb.v
`timescale 1ns/1ps

module counter2_tb;
    reg clk = 0;
    reg shift_ena = 0;
    reg count_ena = 0;
    reg data = 0;
    reg reset = 1;
    wire [3:0] q;

    counter2 dut (
        .clk(clk),
        .shift_ena(shift_ena),
        .count_ena(count_ena),
        .data(data),
        .reset(reset),
        .q(q)
    );

    always #5 clk = ~clk;

    initial begin
        $dumpfile("counter2_tb.vcd");
        $dumpvars(0, counter2_tb);
    end

    initial begin
        $display("Starting counter2_tb");

        // reset
        repeat (2) @(posedge clk);
        reset <= 0;

        // SHIFT phase to match 0 -> 1 -> 2 -> 4 -> 9
        shift_ena <= 1;
        data <= 0; @(posedge clk); #1; if (q !== 4'd0)  $fatal(1, "Step 0 expected 0, got %0d", q);
        data <= 1; @(posedge clk); #1; if (q !== 4'd1)  $fatal(1, "Step 1 expected 1, got %0d", q);
        data <= 0; @(posedge clk); #1; if (q !== 4'd2)  $fatal(1, "Step 2 expected 2, got %0d", q);
        data <= 0; @(posedge clk); #1; if (q !== 4'd4)  $fatal(1, "Step 3 expected 4, got %0d", q);
        data <= 1; @(posedge clk); #1; if (q !== 4'd9)  $fatal(1, "Step 4 expected 9, got %0d", q);
        shift_ena <= 0;

        // COUNT phase: 9,8,7,6,5,4
        count_ena <= 1;
        @(posedge clk); #1; if (q !== 4'd8) $fatal(1, "Count expected 8, got %0d", q);
        @(posedge clk); #1; if (q !== 4'd7) $fatal(1, "Count expected 7, got %0d", q);
        @(posedge clk); #1; if (q !== 4'd6) $fatal(1, "Count expected 6, got %0d", q);
        @(posedge clk); #1; if (q !== 4'd5) $fatal(1, "Count expected 5, got %0d", q);
        @(posedge clk); #1; if (q !== 4'd4) $fatal(1, "Count expected 4, got %0d", q);
        count_ena <= 0;

        $display("counter2_tb passed");
        $finish;
    end
endmodule

counter2_tb.vcd
$date
	Tue Dec 02 18:50:41 2025
$end
$version
	Icarus Verilog
$end
$timescale
	1ps
$end
$scope module counter2_tb $end
$var wire 4 ! q [3:0] $end
$var reg 1 " clk $end
$var reg 1 # count_ena $end
$var reg 1 $ data $end
$var reg 1 % reset $end
$var reg 1 & shift_ena $end
$scope module dut $end
$var wire 1 " clk $end
$var wire 1 # count_ena $end
$var wire 1 $ data $end
$var wire 1 % reset $end
$var wire 1 & shift_ena $end
$var reg 4 ' q [3:0] $end
$upscope $end
$upscope $end
$enddefinitions $end
$comment Show the parameter values. $end
$dumpall
$end
#0
$dumpvars
bx '
0&
1%
0$
0#
0"
bx !
$end
#5000
b0 !
b0 '
1"
#10000
0"
#15000
1&
0%
1"
#20000
0"
#25000
1"
#26000
1$
#30000
0"
#35000
b1 !
b1 '
1"
#36000
0$
#40000
0"
#45000
b10 !
b10 '
1"
#50000
0"
#55000
b100 !
b100 '
1"
#56000
1$
#60000
0"
#65000
b1001 !
b1001 '
1"
#66000
1#
0&
#70000
0"
#75000
b1000 !
b1000 '
1"
#80000
0"
#85000
b111 !
b111 '
1"
#90000
0"
#95000
b110 !
b110 '
1"
#100000
0"
#105000
b101 !
b101 '
1"
#110000
0"
#115000
b100 !
b100 '
1"
#116000
0#
