counter1.v
module counter1 (
    input wire clk,       
    input wire reset,     
    output reg [9:0] count = 10'd0
);

    always @(posedge clk) begin
        if (reset)
            count <= 10'd0;           
        else if (count == 10'd999)
            count <= 10'd0;           
        else
            count <= count + 10'd1;  
    end

endmodule

counter2.v
module counter2 (
    input  wire       clk,        
    input  wire       shift_ena, 
    input  wire       count_ena,  
    input  wire       data,
    input  wire       reset, 
    output reg  [3:0] q          
);
    always @(posedge clk) begin
        if (reset) q <= 4'd0;
        if (shift_ena) begin
            q <= {q[2:0], data};
        end
        if (count_ena) begin
            q <= q - 1;
        end
    end

endmodule

counter3.v
module counter3 (
    input  wire clk,
    input  wire reset,
    input  wire data,
    output reg  start_shifting
);

    localparam S0 = 3'd0;
    localparam S1 = 3'd1;
    localparam S2 = 3'd2;
    localparam S3 = 3'd3;
    localparam S4 = 3'd4;

    reg [2:0] state, next_state;

    always @(posedge clk) begin
        if (reset) begin
            state <= S0;
            start_shifting <= 1'b0;
        end else begin
            state <= next_state;
            if (next_state == S4) begin
                start_shifting <= 1'b1;
                state <= S0;
            end
        end
    end

    always @(*) begin
        case (state)
            S0: begin
                if (data == 1'b1) next_state = S1;
                else              next_state = S0;
            end
            S1: begin
                if (data == 1'b1) next_state = S2;
                else              next_state = S0;
            end
            S2: begin
                if (data == 1'b0) next_state = S3;
                else              next_state = S2;
            end
            S3: begin
                if (data == 1'b1) next_state = S4;
                else              next_state = S0;
            end
            S4: begin
                next_state = S4;
            end
            default: next_state = S0;
        endcase
    end

endmodule

counter4.v
module top_fsm (
    input  wire clk,
    input  wire reset,        
    input  wire data,
    input  wire ack,          

    output wire counting,
    output wire done
);

    localparam S_IDLE  = 2'd0;
    localparam S_SHIFT = 2'd1;
    localparam S_COUNT = 2'd2;
    localparam S_DONE  = 2'd3;

    wire start_shifting;
    wire [3:0] delay;
    reg shift_ena;
    reg count_ena;
    reg counter_done = 0;
    wire [9:0] counter999;


    reg [1:0] state, next_state;
    reg [3:0] repeat_cnt;       
    reg [3:0] delay_reg;        
    reg [1:0] shift_counter;    

    counter3 seq_det (
        .clk(clk),
        .reset(reset),
        .data(data),
        .start_shifting(start_shifting)
    );

    counter2 shift_reg (
        .clk(clk),
        .shift_ena(shift_ena),
        .count_ena(count_ena),
        .data(data),
        .q(delay),
        .reset(reset)
    );

    counter1 cnt_1k (
        .clk(clk),
        .reset(~count_ena),     
        .count(counter999)                
    );
    
    always @(posedge clk) begin
        if (reset) begin
            state        <= S_IDLE;
            repeat_cnt   <= 4'd0;
            delay_reg    <= 4'd0;
            shift_counter <= 2'd0;
        end else begin
            state <= next_state;

            case (state)
                S_SHIFT: begin
                    if (shift_counter == 2'd3) begin
                        delay_reg <= delay;
                    end else if (shift_counter < 2'd3) begin
                        shift_counter <= shift_counter + 1;
                    end else shift_counter <= 0;
                end
                S_COUNT: begin
                    if (counter999 == 10'd999) begin
                        repeat_cnt <= repeat_cnt + 1;
                    end
                end
                default: ;
            endcase
        end
    end

    always @(*) begin
        next_state = state;
        shift_ena  = 1'b0;
        count_ena  = 1'b0;

        case (state)
            S_IDLE: begin
                if (start_shifting) begin
                    next_state = S_SHIFT;
                end
            end

            S_SHIFT: begin
                shift_ena = 1'b1;
                if (shift_counter == 2'd3) begin
                    next_state = S_COUNT;
                end
            end

            S_COUNT: begin
                count_ena = 1'b1;
                if (repeat_cnt == delay_reg) begin
                    next_state = S_DONE;
                end
            end

            S_DONE: begin
                if (ack) begin
                    next_state = S_IDLE;
                end
            end

            default: next_state = S_IDLE;
        endcase
    end

    assign counting = (state == S_COUNT);
    assign done = (state == S_DONE);
endmodule

counter4_tb.v
`timescale 1ns/1ps

module counter4_tb;
    reg clk = 0;
    reg reset = 1;
    reg data = 0;
    reg ack = 0;
    wire counting;
    wire done;

    top_fsm dut (
        .clk(clk),
        .reset(reset),
        .data(data),
        .ack(ack),
        .counting(counting),
        .done(done)
    );

    always #5 clk = ~clk;

    initial begin
        $dumpfile("counter4_tb.vcd");
        $dumpvars(0, counter4_tb);
    end

    task send_bit(input bit bitval);
        begin
            data = bitval;
            @(posedge clk);
        end
    endtask

    always @(posedge clk) begin
        if ($test$plusargs("trace")) begin
            $display("%0t state=%0d shift_cnt=%0d delay=%0d delay_reg=%0d q=%0d counting=%b done=%b data=%b",
                     $time, dut.state, dut.shift_counter, dut.delay, dut.delay_reg, dut.shift_reg.q, counting, done, data);
        end
    end

    initial begin
        $display("Starting counter4_tb");

        // release reset
        repeat (2) @(posedge clk);
        reset <= 0;

        // Single sequence per truth table example: delay value 1
        kick_pattern();
        run_sequence(4'b0001, 4'd1, 2000);

        $display("counter4_tb passed");
        $finish;
    end

    task kick_pattern;
        begin
            // pattern 1101 to raise start_shifting
            send_bit(1'b1);
            send_bit(1'b1);
            send_bit(1'b0);
            send_bit(1'b1);
        end
    endtask

    task run_sequence(input [3:0] bits, input [3:0] expected_delay, input integer max_cycles);
        integer i;
        integer cycles;
        begin
            // prime first bit before SHIFT to avoid stale data
            data = bits[3];
            wait (dut.state == 2'd1);
            @(posedge clk); // first shift

            // remaining 3 bits
            for (i = 2; i >= 0; i = i - 1) begin
                data = bits[i];
                @(posedge clk);
            end

            // wait for counting state
            wait (dut.state == 2'd2);
            if (dut.delay_reg !== expected_delay) $fatal(1, "delay_reg mismatch, got %0d expected %0d", dut.delay_reg, expected_delay);

            // wait for done with a bound
            cycles = 0;
            while (done !== 1'b1 && cycles < max_cycles) begin
                @(posedge clk);
                cycles = cycles + 1;
            end
            if (done !== 1'b1) $fatal(1, "FSM did not assert done for delay %0d", expected_delay);

            // acknowledge and return to idle
            ack <= 1'b1;
            @(posedge clk);
            ack <= 1'b0;
            @(posedge clk);
        end
    endtask
endmodule

counter4_tb.vcd
$date
	Tue Dec 02 18:51:29 2025
$end
$version
	Icarus Verilog
$end
$timescale
	1ps
$end
$scope module counter4_tb $end
$var wire 1 ! done $end
$var wire 1 " counting $end
$var reg 1 # ack $end
$var reg 1 $ clk $end
$var reg 1 % data $end
$var reg 1 & reset $end
$scope module dut $end
$var wire 1 # ack $end
$var wire 1 $ clk $end
$var wire 1 % data $end
$var wire 1 & reset $end
$var wire 1 ' start_shifting $end
$var wire 1 ! done $end
$var wire 4 ( delay [3:0] $end
$var wire 1 " counting $end
$var wire 10 ) counter999 [9:0] $end
$var parameter 2 * S_COUNT $end
$var parameter 2 + S_DONE $end
$var parameter 2 , S_IDLE $end
$var parameter 2 - S_SHIFT $end
$var reg 1 . count_ena $end
$var reg 1 / counter_done $end
$var reg 4 0 delay_reg [3:0] $end
$var reg 2 1 next_state [1:0] $end
$var reg 4 2 repeat_cnt [3:0] $end
$var reg 2 3 shift_counter [1:0] $end
$var reg 1 4 shift_ena $end
$var reg 2 5 state [1:0] $end
$scope module cnt_1k $end
$var wire 1 $ clk $end
$var wire 1 6 reset $end
$var reg 10 7 count [9:0] $end
$upscope $end
$scope module seq_det $end
$var wire 1 $ clk $end
$var wire 1 % data $end
$var wire 1 & reset $end
$var parameter 3 8 S0 $end
$var parameter 3 9 S1 $end
$var parameter 3 : S2 $end
$var parameter 3 ; S3 $end
$var parameter 3 < S4 $end
$var reg 3 = next_state [2:0] $end
$var reg 1 ' start_shifting $end
$var reg 3 > state [2:0] $end
$upscope $end
$scope module shift_reg $end
$var wire 1 $ clk $end
$var wire 1 . count_ena $end
$var wire 1 % data $end
$var wire 1 & reset $end
$var wire 1 4 shift_ena $end
$var reg 4 ? q [3:0] $end
$upscope $end
$upscope $end
$scope task kick_pattern $end
$upscope $end
$scope task run_sequence $end
$var reg 4 @ bits [3:0] $end
$var reg 4 A expected_delay [3:0] $end
$var integer 32 B cycles [31:0] $end
$var integer 32 C i [31:0] $end
$var integer 32 D max_cycles [31:0] $end
$upscope $end
$scope task send_bit $end
$var reg 1 E bitval $end
$upscope $end
$upscope $end
$enddefinitions $end
$comment Show the parameter values. $end
$dumpall
b100 <
b11 ;
b10 :
b1 9
b0 8
b1 -
b0 ,
b11 +
b10 *
$end
#0
$dumpvars
0E
bx D
bx C
bx B
bx A
bx @
bx ?
bx >
bx =
b0 7
x6
bx 5
x4
bx 3
bx 2
bx 1
bx 0
0/
x.
b0 )
bx (
x'
1&
0%
0$
0#
x"
x!
$end
#5000
16
b0 =
0.
04
b0 1
0'
b0 >
b0 (
b0 ?
b1 )
b1 7
b0 3
b0 0
b0 2
0"
0!
b0 5
1$
#10000
0$
#15000
0&
b0 )
b0 7
b1 =
1%
1E
1$
#20000
0$
#25000
b10 =
b1 >
1$
#30000
0$
#35000
b10 >
b11 =
0%
0E
1$
#40000
0$
#45000
b11 >
b100 =
1%
1E
1$
#50000
0$
#55000
b1 1
1'
b0 >
b0 =
0%
b11111010000 D
b1 A
b1 @
1$
#60000
0$
#65000
14
b1 5
1$
#70000
0$
#75000
14
b1 3
b10 C
1$
#80000
0$
#85000
14
b10 3
b1 C
1$
#90000
0$
#95000
b10 1
14
b11 3
b1 (
b1 ?
b1 =
1%
b0 C
1$
#100000
0$
#105000
06
b10 =
1.
04
b0 B
b1 >
b11 (
b11 ?
b1 0
1"
b10 5
b11111111111111111111111111111111 C
1$
#110000
0$
#115000
b1 )
b1 7
b10 (
b10 ?
b10 >
b1 B
1$
#120000
0$
#125000
b1 (
b1 ?
b10 )
b10 7
b10 B
1$
#130000
0$
#135000
b11 )
b11 7
b0 (
b0 ?
b11 B
1$
#140000
0$
#145000
b1111 (
b1111 ?
b100 )
b100 7
b100 B
1$
#150000
0$
#155000
b101 )
b101 7
b1110 (
b1110 ?
b101 B
1$
#160000
0$
#165000
b1101 (
b1101 ?
b110 )
b110 7
b110 B
1$
#170000
0$
#175000
b111 )
b111 7
b1100 (
b1100 ?
b111 B
1$
#180000
0$
#185000
b1011 (
b1011 ?
b1000 )
b1000 7
b1000 B
1$
#190000
0$
#195000
b1001 )
b1001 7
b1010 (
b1010 ?
b1001 B
1$
#200000
0$
#205000
b1001 (
b1001 ?
b1010 )
b1010 7
b1010 B
1$
#210000
0$
#215000
b1011 )
b1011 7
b1000 (
b1000 ?
b1011 B
1$
#220000
0$
#225000
b111 (
b111 ?
b1100 )
b1100 7
b1100 B
1$
#230000
0$
#235000
b1101 )
b1101 7
b110 (
b110 ?
b1101 B
1$
#240000
0$
#245000
b101 (
b101 ?
b1110 )
b1110 7
b1110 B
1$
#250000
0$
#255000
b1111 )
b1111 7
b100 (
b100 ?
b1111 B
1$
#260000
0$
#265000
b11 (
b11 ?
b10000 )
b10000 7
b10000 B
1$
#270000
0$
#275000
b10001 )
b10001 7
b10 (
b10 ?
b10001 B
1$
#280000
0$
#285000
b1 (
b1 ?
b10010 )
b10010 7
b10010 B
1$
#290000
0$
#295000
b10011 )
b10011 7
b0 (
b0 ?
b10011 B
1$
#300000
0$
#305000
b1111 (
b1111 ?
b10100 )
b10100 7
b10100 B
1$
#310000
0$
#315000
b10101 )
b10101 7
b1110 (
b1110 ?
b10101 B
1$
#320000
0$
#325000
b1101 (
b1101 ?
b10110 )
b10110 7
b10110 B
1$
#330000
0$
#335000
b10111 )
b10111 7
b1100 (
b1100 ?
b10111 B
1$
#340000
0$
#345000
b1011 (
b1011 ?
b11000 )
b11000 7
b11000 B
1$
#350000
0$
#355000
b11001 )
b11001 7
b1010 (
b1010 ?
b11001 B
1$
#360000
0$
#365000
b1001 (
b1001 ?
b11010 )
b11010 7
b11010 B
1$
#370000
0$
#375000
b11011 )
b11011 7
b1000 (
b1000 ?
b11011 B
1$
#380000
0$
#385000
b111 (
b111 ?
b11100 )
b11100 7
b11100 B
1$
#390000
0$
#395000
b11101 )
b11101 7
b110 (
b110 ?
b11101 B
1$
#400000
0$
#405000
b101 (
b101 ?
b11110 )
b11110 7
b11110 B
1$
#410000
0$
#415000
b11111 )
b11111 7
b100 (
b100 ?
b11111 B
1$
#420000
0$
#425000
b11 (
b11 ?
b100000 )
b100000 7
b100000 B
1$
#430000
0$
#435000
b100001 )
b100001 7
b10 (
b10 ?
b100001 B
1$
#440000
0$
#445000
b1 (
b1 ?
b100010 )
b100010 7
b100010 B
1$
#450000
0$
#455000
b100011 )
b100011 7
b0 (
b0 ?
b100011 B
1$
#460000
0$
#465000
b1111 (
b1111 ?
b100100 )
b100100 7
b100100 B
1$
#470000
0$
#475000
b100101 )
b100101 7
b1110 (
b1110 ?
b100101 B
1$
#480000
0$
#485000
b1101 (
b1101 ?
b100110 )
b100110 7
b100110 B
1$
#490000
0$
#495000
b100111 )
b100111 7
b1100 (
b1100 ?
b100111 B
1$
#500000
0$
#505000
b1011 (
b1011 ?
b101000 )
b101000 7
b101000 B
1$
#510000
0$
#515000
b101001 )
b101001 7
b1010 (
b1010 ?
b101001 B
1$
#520000
0$
#525000
b1001 (
b1001 ?
b101010 )
b101010 7
b101010 B
1$
#530000
0$
#535000
b101011 )
b101011 7
b1000 (
b1000 ?
b101011 B
1$
#540000
0$
#545000
b111 (
b111 ?
b101100 )
b101100 7
b101100 B
1$
#550000
0$
#555000
b101101 )
b101101 7
b110 (
b110 ?
b101101 B
1$
#560000
0$
#565000
b101 (
b101 ?
b101110 )
b101110 7
b101110 B
1$
#570000
0$
#575000
b101111 )
b101111 7
b100 (
b100 ?
b101111 B
1$
#580000
0$
#585000
b11 (
b11 ?
b110000 )
b110000 7
b110000 B
1$
#590000
0$
#595000
b110001 )
b110001 7
b10 (
b10 ?
b110001 B
1$
#600000
0$
#605000
b1 (
b1 ?
b110010 )
b110010 7
b110010 B
1$
#610000
0$
#615000
b110011 )
b110011 7
b0 (
b0 ?
b110011 B
1$
#620000
0$
#625000
b1111 (
b1111 ?
b110100 )
b110100 7
b110100 B
1$
#630000
0$
#635000
b110101 )
b110101 7
b1110 (
b1110 ?
b110101 B
1$
#640000
0$
#645000
b1101 (
b1101 ?
b110110 )
b110110 7
b110110 B
1$
#650000
0$
#655000
b110111 )
b110111 7
b1100 (
b1100 ?
b110111 B
1$
#660000
0$
#665000
b1011 (
b1011 ?
b111000 )
b111000 7
b111000 B
1$
#670000
0$
#675000
b111001 )
b111001 7
b1010 (
b1010 ?
b111001 B
1$
#680000
0$
#685000
b1001 (
b1001 ?
b111010 )
b111010 7
b111010 B
1$
#690000
0$
#695000
b111011 )
b111011 7
b1000 (
b1000 ?
b111011 B
1$
#700000
0$
#705000
b111 (
b111 ?
b111100 )
b111100 7
b111100 B
1$
#710000
0$
#715000
b111101 )
b111101 7
b110 (
b110 ?
b111101 B
1$
#720000
0$
#725000
b101 (
b101 ?
b111110 )
b111110 7
b111110 B
1$
#730000
0$
#735000
b111111 )
b111111 7
b100 (
b100 ?
b111111 B
1$
#740000
0$
#745000
b11 (
b11 ?
b1000000 )
b1000000 7
b1000000 B
1$
#750000
0$
#755000
b1000001 )
b1000001 7
b10 (
b10 ?
b1000001 B
1$
#760000
0$
#765000
b1 (
b1 ?
b1000010 )
b1000010 7
b1000010 B
1$
#770000
0$
#775000
b1000011 )
b1000011 7
b0 (
b0 ?
b1000011 B
1$
#780000
0$
#785000
b1111 (
b1111 ?
b1000100 )
b1000100 7
b1000100 B
1$
#790000
0$
#795000
b1000101 )
b1000101 7
b1110 (
b1110 ?
b1000101 B
1$
#800000
0$
#805000
b1101 (
b1101 ?
b1000110 )
b1000110 7
b1000110 B
1$
#810000
0$
#815000
b1000111 )
b1000111 7
b1100 (
b1100 ?
b1000111 B
1$
#820000
0$
#825000
b1011 (
b1011 ?
b1001000 )
b1001000 7
b1001000 B
1$
#830000
0$
#835000
b1001001 )
b1001001 7
b1010 (
b1010 ?
b1001001 B
1$
#840000
0$
#845000
b1001 (
b1001 ?
b1001010 )
b1001010 7
b1001010 B
1$
#850000
0$
#855000
b1001011 )
b1001011 7
b1000 (
b1000 ?
b1001011 B
1$
#860000
0$
#865000
b111 (
b111 ?
b1001100 )
b1001100 7
b1001100 B
1$
#870000
0$
#875000
b1001101 )
b1001101 7
b110 (
b110 ?
b1001101 B
1$
#880000
0$
#885000
b101 (
b101 ?
b1001110 )
b1001110 7
b1001110 B
1$
#890000
0$
#895000
b1001111 )
b1001111 7
b100 (
b100 ?
b1001111 B
1$
#900000
0$
#905000
b11 (
b11 ?
b1010000 )
b1010000 7
b1010000 B
1$
#910000
0$
#915000
b1010001 )
b1010001 7
b10 (
b10 ?
b1010001 B
1$
#920000
0$
#925000
b1 (
b1 ?
b1010010 )
b1010010 7
b1010010 B
1$
#930000
0$
#935000
b1010011 )
b1010011 7
b0 (
b0 ?
b1010011 B
1$
#940000
0$
#945000
b1111 (
b1111 ?
b1010100 )
b1010100 7
b1010100 B
1$
#950000
0$
#955000
b1010101 )
b1010101 7
b1110 (
b1110 ?
b1010101 B
1$
#960000
0$
#965000
b1101 (
b1101 ?
b1010110 )
b1010110 7
b1010110 B
1$
#970000
0$
#975000
b1010111 )
b1010111 7
b1100 (
b1100 ?
b1010111 B
1$
#980000
0$
#985000
b1011 (
b1011 ?
b1011000 )
b1011000 7
b1011000 B
1$
#990000
0$
#995000
b1011001 )
b1011001 7
b1010 (
b1010 ?
b1011001 B
1$
#1000000
0$
#1005000
b1001 (
b1001 ?
b1011010 )
b1011010 7
b1011010 B
1$
#1010000
0$
#1015000
b1011011 )
b1011011 7
b1000 (
b1000 ?
b1011011 B
1$
#1020000
0$
#1025000
b111 (
b111 ?
b1011100 )
b1011100 7
b1011100 B
1$
#1030000
0$
#1035000
b1011101 )
b1011101 7
b110 (
b110 ?
b1011101 B
1$
#1040000
0$
#1045000
b101 (
b101 ?
b1011110 )
b1011110 7
b1011110 B
1$
#1050000
0$
#1055000
b1011111 )
b1011111 7
b100 (
b100 ?
b1011111 B
1$
#1060000
0$
#1065000
b11 (
b11 ?
b1100000 )
b1100000 7
b1100000 B
1$
#1070000
0$
#1075000
b1100001 )
b1100001 7
b10 (
b10 ?
b1100001 B
1$
#1080000
0$
#1085000
b1 (
b1 ?
b1100010 )
b1100010 7
b1100010 B
1$
#1090000
0$
#1095000
b1100011 )
b1100011 7
b0 (
b0 ?
b1100011 B
1$
#1100000
0$
#1105000
b1111 (
b1111 ?
b1100100 )
b1100100 7
b1100100 B
1$
#1110000
0$
#1115000
b1100101 )
b1100101 7
b1110 (
b1110 ?
b1100101 B
1$
#1120000
0$
#1125000
b1101 (
b1101 ?
b1100110 )
b1100110 7
b1100110 B
1$
#1130000
0$
#1135000
b1100111 )
b1100111 7
b1100 (
b1100 ?
b1100111 B
1$
#1140000
0$
#1145000
b1011 (
b1011 ?
b1101000 )
b1101000 7
b1101000 B
1$
#1150000
0$
#1155000
b1101001 )
b1101001 7
b1010 (
b1010 ?
b1101001 B
1$
#1160000
0$
#1165000
b1001 (
b1001 ?
b1101010 )
b1101010 7
b1101010 B
1$
#1170000
0$
#1175000
b1101011 )
b1101011 7
b1000 (
b1000 ?
b1101011 B
1$
#1180000
0$
#1185000
b111 (
b111 ?
b1101100 )
b1101100 7
b1101100 B
1$
#1190000
0$
#1195000
b1101101 )
b1101101 7
b110 (
b110 ?
b1101101 B
1$
#1200000
0$
#1205000
b101 (
b101 ?
b1101110 )
b1101110 7
b1101110 B
1$
#1210000
0$
#1215000
b1101111 )
b1101111 7
b100 (
b100 ?
b1101111 B
1$
#1220000
0$
#1225000
b11 (
b11 ?
b1110000 )
b1110000 7
b1110000 B
1$
#1230000
0$
#1235000
b1110001 )
b1110001 7
b10 (
b10 ?
b1110001 B
1$
#1240000
0$
#1245000
b1 (
b1 ?
b1110010 )
b1110010 7
b1110010 B
1$
#1250000
0$
#1255000
b1110011 )
b1110011 7
b0 (
b0 ?
b1110011 B
1$
#1260000
0$
#1265000
b1111 (
b1111 ?
b1110100 )
b1110100 7
b1110100 B
1$
#1270000
0$
#1275000
b1110101 )
b1110101 7
b1110 (
b1110 ?
b1110101 B
1$
#1280000
0$
#1285000
b1101 (
b1101 ?
b1110110 )
b1110110 7
b1110110 B
1$
#1290000
0$
#1295000
b1110111 )
b1110111 7
b1100 (
b1100 ?
b1110111 B
1$
#1300000
0$
#1305000
b1011 (
b1011 ?
b1111000 )
b1111000 7
b1111000 B
1$
#1310000
0$
#1315000
b1111001 )
b1111001 7
b1010 (
b1010 ?
b1111001 B
1$
#1320000
0$
#1325000
b1001 (
b1001 ?
b1111010 )
b1111010 7
b1111010 B
1$
#1330000
0$
#1335000
b1111011 )
b1111011 7
b1000 (
b1000 ?
b1111011 B
1$
#1340000
0$
#1345000
b111 (
b111 ?
b1111100 )
b1111100 7
b1111100 B
1$
#1350000
0$
#1355000
b1111101 )
b1111101 7
b110 (
b110 ?
b1111101 B
1$
#1360000
0$
#1365000
b101 (
b101 ?
b1111110 )
b1111110 7
b1111110 B
1$
#1370000
0$
#1375000
b1111111 )
b1111111 7
b100 (
b100 ?
b1111111 B
1$
#1380000
0$
#1385000
b11 (
b11 ?
b10000000 )
b10000000 7
b10000000 B
1$
#1390000
0$
#1395000
b10000001 )
b10000001 7
b10 (
b10 ?
b10000001 B
1$
#1400000
0$
#1405000
b1 (
b1 ?
b10000010 )
b10000010 7
b10000010 B
1$
#1410000
0$
#1415000
b10000011 )
b10000011 7
b0 (
b0 ?
b10000011 B
1$
#1420000
0$
#1425000
b1111 (
b1111 ?
b10000100 )
b10000100 7
b10000100 B
1$
#1430000
0$
#1435000
b10000101 )
b10000101 7
b1110 (
b1110 ?
b10000101 B
1$
#1440000
0$
#1445000
b1101 (
b1101 ?
b10000110 )
b10000110 7
b10000110 B
1$
#1450000
0$
#1455000
b10000111 )
b10000111 7
b1100 (
b1100 ?
b10000111 B
1$
#1460000
0$
#1465000
b1011 (
b1011 ?
b10001000 )
b10001000 7
b10001000 B
1$
#1470000
0$
#1475000
b10001001 )
b10001001 7
b1010 (
b1010 ?
b10001001 B
1$
#1480000
0$
#1485000
b1001 (
b1001 ?
b10001010 )
b10001010 7
b10001010 B
1$
#1490000
0$
#1495000
b10001011 )
b10001011 7
b1000 (
b1000 ?
b10001011 B
1$
#1500000
0$
#1505000
b111 (
b111 ?
b10001100 )
b10001100 7
b10001100 B
1$
#1510000
0$
#1515000
b10001101 )
b10001101 7
b110 (
b110 ?
b10001101 B
1$
#1520000
0$
#1525000
b101 (
b101 ?
b10001110 )
b10001110 7
b10001110 B
1$
#1530000
0$
#1535000
b10001111 )
b10001111 7
b100 (
b100 ?
b10001111 B
1$
#1540000
0$
#1545000
b11 (
b11 ?
b10010000 )
b10010000 7
b10010000 B
1$
#1550000
0$
#1555000
b10010001 )
b10010001 7
b10 (
b10 ?
b10010001 B
1$
#1560000
0$
#1565000
b1 (
b1 ?
b10010010 )
b10010010 7
b10010010 B
1$
#1570000
0$
#1575000
b10010011 )
b10010011 7
b0 (
b0 ?
b10010011 B
1$
#1580000
0$
#1585000
b1111 (
b1111 ?
b10010100 )
b10010100 7
b10010100 B
1$
#1590000
0$
#1595000
b10010101 )
b10010101 7
b1110 (
b1110 ?
b10010101 B
1$
#1600000
0$
#1605000
b1101 (
b1101 ?
b10010110 )
b10010110 7
b10010110 B
1$
#1610000
0$
#1615000
b10010111 )
b10010111 7
b1100 (
b1100 ?
b10010111 B
1$
#1620000
0$
#1625000
b1011 (
b1011 ?
b10011000 )
b10011000 7
b10011000 B
1$
#1630000
0$
#1635000
b10011001 )
b10011001 7
b1010 (
b1010 ?
b10011001 B
1$
#1640000
0$
#1645000
b1001 (
b1001 ?
b10011010 )
b10011010 7
b10011010 B
1$
#1650000
0$
#1655000
b10011011 )
b10011011 7
b1000 (
b1000 ?
b10011011 B
1$
#1660000
0$
#1665000
b111 (
b111 ?
b10011100 )
b10011100 7
b10011100 B
1$
#1670000
0$
#1675000
b10011101 )
b10011101 7
b110 (
b110 ?
b10011101 B
1$
#1680000
0$
#1685000
b101 (
b101 ?
b10011110 )
b10011110 7
b10011110 B
1$
#1690000
0$
#1695000
b10011111 )
b10011111 7
b100 (
b100 ?
b10011111 B
1$
#1700000
0$
#1705000
b11 (
b11 ?
b10100000 )
b10100000 7
b10100000 B
1$
#1710000
0$
#1715000
b10100001 )
b10100001 7
b10 (
b10 ?
b10100001 B
1$
#1720000
0$
#1725000
b1 (
b1 ?
b10100010 )
b10100010 7
b10100010 B
1$
#1730000
0$
#1735000
b10100011 )
b10100011 7
b0 (
b0 ?
b10100011 B
1$
#1740000
0$
#1745000
b1111 (
b1111 ?
b10100100 )
b10100100 7
b10100100 B
1$
#1750000
0$
#1755000
b10100101 )
b10100101 7
b1110 (
b1110 ?
b10100101 B
1$
#1760000
0$
#1765000
b1101 (
b1101 ?
b10100110 )
b10100110 7
b10100110 B
1$
#1770000
0$
#1775000
b10100111 )
b10100111 7
b1100 (
b1100 ?
b10100111 B
1$
#1780000
0$
#1785000
b1011 (
b1011 ?
b10101000 )
b10101000 7
b10101000 B
1$
#1790000
0$
#1795000
b10101001 )
b10101001 7
b1010 (
b1010 ?
b10101001 B
1$
#1800000
0$
#1805000
b1001 (
b1001 ?
b10101010 )
b10101010 7
b10101010 B
1$
#1810000
0$
#1815000
b10101011 )
b10101011 7
b1000 (
b1000 ?
b10101011 B
1$
#1820000
0$
#1825000
b111 (
b111 ?
b10101100 )
b10101100 7
b10101100 B
1$
#1830000
0$
#1835000
b10101101 )
b10101101 7
b110 (
b110 ?
b10101101 B
1$
#1840000
0$
#1845000
b101 (
b101 ?
b10101110 )
b10101110 7
b10101110 B
1$
#1850000
0$
#1855000
b10101111 )
b10101111 7
b100 (
b100 ?
b10101111 B
1$
#1860000
0$
#1865000
b11 (
b11 ?
b10110000 )
b10110000 7
b10110000 B
1$
#1870000
0$
#1875000
b10110001 )
b10110001 7
b10 (
b10 ?
b10110001 B
1$
#1880000
0$
#1885000
b1 (
b1 ?
b10110010 )
b10110010 7
b10110010 B
1$
#1890000
0$
#1895000
b10110011 )
b10110011 7
b0 (
b0 ?
b10110011 B
1$
#1900000
0$
#1905000
b1111 (
b1111 ?
b10110100 )
b10110100 7
b10110100 B
1$
#1910000
0$
#1915000
b10110101 )
b10110101 7
b1110 (
b1110 ?
b10110101 B
1$
#1920000
0$
#1925000
b1101 (
b1101 ?
b10110110 )
b10110110 7
b10110110 B
1$
#1930000
0$
#1935000
b10110111 )
b10110111 7
b1100 (
b1100 ?
b10110111 B
1$
#1940000
0$
#1945000
b1011 (
b1011 ?
b10111000 )
b10111000 7
b10111000 B
1$
#1950000
0$
#1955000
b10111001 )
b10111001 7
b1010 (
b1010 ?
b10111001 B
1$
#1960000
0$
#1965000
b1001 (
b1001 ?
b10111010 )
b10111010 7
b10111010 B
1$
#1970000
0$
#1975000
b10111011 )
b10111011 7
b1000 (
b1000 ?
b10111011 B
1$
#1980000
0$
#1985000
b111 (
b111 ?
b10111100 )
b10111100 7
b10111100 B
1$
#1990000
0$
#1995000
b10111101 )
b10111101 7
b110 (
b110 ?
b10111101 B
1$
#2000000
0$
#2005000
b101 (
b101 ?
b10111110 )
b10111110 7
b10111110 B
1$
#2010000
0$
#2015000
b10111111 )
b10111111 7
b100 (
b100 ?
b10111111 B
1$
#2020000
0$
#2025000
b11 (
b11 ?
b11000000 )
b11000000 7
b11000000 B
1$
#2030000
0$
#2035000
b11000001 )
b11000001 7
b10 (
b10 ?
b11000001 B
1$
#2040000
0$
#2045000
b1 (
b1 ?
b11000010 )
b11000010 7
b11000010 B
1$
#2050000
0$
#2055000
b11000011 )
b11000011 7
b0 (
b0 ?
b11000011 B
1$
#2060000
0$
#2065000
b1111 (
b1111 ?
b11000100 )
b11000100 7
b11000100 B
1$
#2070000
0$
#2075000
b11000101 )
b11000101 7
b1110 (
b1110 ?
b11000101 B
1$
#2080000
0$
#2085000
b1101 (
b1101 ?
b11000110 )
b11000110 7
b11000110 B
1$
#2090000
0$
#2095000
b11000111 )
b11000111 7
b1100 (
b1100 ?
b11000111 B
1$
#2100000
0$
#2105000
b1011 (
b1011 ?
b11001000 )
b11001000 7
b11001000 B
1$
#2110000
0$
#2115000
b11001001 )
b11001001 7
b1010 (
b1010 ?
b11001001 B
1$
#2120000
0$
#2125000
b1001 (
b1001 ?
b11001010 )
b11001010 7
b11001010 B
1$
#2130000
0$
#2135000
b11001011 )
b11001011 7
b1000 (
b1000 ?
b11001011 B
1$
#2140000
0$
#2145000
b111 (
b111 ?
b11001100 )
b11001100 7
b11001100 B
1$
#2150000
0$
#2155000
b11001101 )
b11001101 7
b110 (
b110 ?
b11001101 B
1$
#2160000
0$
#2165000
b101 (
b101 ?
b11001110 )
b11001110 7
b11001110 B
1$
#2170000
0$
#2175000
b11001111 )
b11001111 7
b100 (
b100 ?
b11001111 B
1$
#2180000
0$
#2185000
b11 (
b11 ?
b11010000 )
b11010000 7
b11010000 B
1$
#2190000
0$
#2195000
b11010001 )
b11010001 7
b10 (
b10 ?
b11010001 B
1$
#2200000
0$
#2205000
b1 (
b1 ?
b11010010 )
b11010010 7
b11010010 B
1$
#2210000
0$
#2215000
b11010011 )
b11010011 7
b0 (
b0 ?
b11010011 B
1$
#2220000
0$
#2225000
b1111 (
b1111 ?
b11010100 )
b11010100 7
b11010100 B
1$
#2230000
0$
#2235000
b11010101 )
b11010101 7
b1110 (
b1110 ?
b11010101 B
1$
#2240000
0$
#2245000
b1101 (
b1101 ?
b11010110 )
b11010110 7
b11010110 B
1$
#2250000
0$
#2255000
b11010111 )
b11010111 7
b1100 (
b1100 ?
b11010111 B
1$
#2260000
0$
#2265000
b1011 (
b1011 ?
b11011000 )
b11011000 7
b11011000 B
1$
#2270000
0$
#2275000
b11011001 )
b11011001 7
b1010 (
b1010 ?
b11011001 B
1$
#2280000
0$
#2285000
b1001 (
b1001 ?
b11011010 )
b11011010 7
b11011010 B
1$
#2290000
0$
#2295000
b11011011 )
b11011011 7
b1000 (
b1000 ?
b11011011 B
1$
#2300000
0$
