lab3/comb_part3.v
module comb_part3 (
    input  wire [3:0] a,
    input  wire [3:0] b,
    input  wire [3:0] c,
    input  wire [3:0] d,
    input  wire [3:0] e,
    output reg  [3:0] q
);
    always @* begin
        case (c)
            4'h0: q = b;
            4'h1: q = e;
            4'h2: q = a;
            4'h3: q = d;
            default: q = 4'hf;
        endcase
    end
endmodule

lab3/comb_part3_tb.v
`timescale 1ns / 1ps

module comb_part3_tb;
    reg [3:0] a, b, c, d, e;
    wire [3:0] q;

    comb_part3 dut (
        .a(a),
        .b(b),
        .c(c),
        .d(d),
        .e(e),
        .q(q)
    );

    function automatic [3:0] expected(input [3:0] sel,
                                      input [3:0] va,
                                      input [3:0] vb,
                                      input [3:0] vd,
                                      input [3:0] ve);
        case (sel)
            4'h0: expected = vb;
            4'h1: expected = ve;
            4'h2: expected = va;
            4'h3: expected = vd;
            default: expected = 4'hf;
        endcase
    endfunction

    integer i;

    task check_set;
        begin
            for (i = 0; i < 16; i = i + 1) begin
                c = i[3:0];
                #5;
                if (q !== expected(c, a, b, d, e)) begin
                    $display("Mismatch at time %0t: c=%0h -> q=%0h expected=%0h (a=%0h b=%0h d=%0h e=%0h)",
                             $time, c, q, expected(c, a, b, d, e), a, b, d, e);
                    $fatal;
                end
            end
        end
    endtask

    initial begin
        $dumpfile("comb_part3_wave_tb.vcd");
        $dumpvars(0, comb_part3_tb);

        a = 4'ha; b = 4'hb; d = 4'hd; e = 4'he;
        check_set();

        #20;
        a = 4'h1; b = 4'h2; d = 4'h3; e = 4'h4;
        check_set();

        #20;
        a = 4'h5; b = 4'h6; d = 4'h7; e = 4'h8;
        check_set();

        #10 $finish;
    end
endmodule

lab3/comb_part3_wave_tb.vcd
$date
	Tue Nov 04 14:33:45 2025
$end
$version
	Icarus Verilog
$end
$timescale
	1ps
$end
$scope module comb_part3_tb $end
$var wire 4 ! q [3:0] $end
$var reg 4 " a [3:0] $end
$var reg 4 # b [3:0] $end
$var reg 4 $ c [3:0] $end
$var reg 4 % d [3:0] $end
$var reg 4 & e [3:0] $end
$var integer 32 ' i [31:0] $end
$scope function expected $end
$upscope $end
$scope module dut $end
$var wire 4 ( a [3:0] $end
$var wire 4 ) b [3:0] $end
$var wire 4 * c [3:0] $end
$var wire 4 + d [3:0] $end
$var wire 4 , e [3:0] $end
$var reg 4 - q [3:0] $end
$upscope $end
$scope task check_set $end
$upscope $end
$upscope $end
$enddefinitions $end
$comment Show the parameter values. $end
$dumpall
$end
#0
$dumpvars
b1011 -
b1110 ,
b1101 +
b0 *
b1011 )
b1010 (
b0 '
b1110 &
b1101 %
b0 $
b1011 #
b1010 "
b1011 !
$end
#5000
b1110 !
b1110 -
b1 $
b1 *
b1 '
#10000
b1010 !
b1010 -
b10 $
b10 *
b10 '
#15000
b1101 !
b1101 -
b11 $
b11 *
b11 '
#20000
b1111 !
b1111 -
b100 $
b100 *
b100 '
#25000
b101 $
b101 *
b101 '
#30000
b110 $
b110 *
b110 '
#35000
b111 $
b111 *
b111 '
#40000
b1000 $
b1000 *
b1000 '
#45000
b1001 $
b1001 *
b1001 '
#50000
b1010 $
b1010 *
b1010 '
#55000
b1011 $
b1011 *
b1011 '
#60000
b1100 $
b1100 *
b1100 '
#65000
b1101 $
b1101 *
b1101 '
#70000
b1110 $
b1110 *
b1110 '
#75000
b1111 $
b1111 *
b1111 '
#80000
b10000 '
#100000
b10 !
b10 -
b0 $
b0 *
b0 '
b100 &
b100 ,
b11 %
b11 +
b10 #
b10 )
b1 "
b1 (
#105000
b100 !
b100 -
b1 $
b1 *
b1 '
#110000
b1 !
b1 -
b10 $
b10 *
b10 '
#115000
b11 !
b11 -
b11 $
b11 *
b11 '
#120000
b1111 !
b1111 -
b100 $
b100 *
b100 '
#125000
b101 $
b101 *
b101 '
#130000
b110 $
b110 *
b110 '
#135000
b111 $
b111 *
b111 '
#140000
b1000 $
b1000 *
b1000 '
#145000
b1001 $
b1001 *
b1001 '
#150000
b1010 $
b1010 *
b1010 '
#155000
b1011 $
b1011 *
b1011 '
#160000
b1100 $
b1100 *
b1100 '
#165000
b1101 $
b1101 *
b1101 '
#170000
b1110 $
b1110 *
b1110 '
#175000
b1111 $
b1111 *
b1111 '
#180000
b10000 '
#200000
b110 !
b110 -
b0 $
b0 *
b0 '
b1000 &
b1000 ,
b111 %
b111 +
b110 #
b110 )
b101 "
b101 (
#205000
b1000 !
b1000 -
b1 $
b1 *
b1 '
#210000
b101 !
b101 -
b10 $
b10 *
b10 '
#215000
b111 !
b111 -
b11 $
b11 *
b11 '
#220000
b1111 !
b1111 -
b100 $
b100 *
b100 '
#225000
b101 $
b101 *
b101 '
#230000
b110 $
b110 *
b110 '
#235000
b111 $
b111 *
b111 '
#240000
b1000 $
b1000 *
b1000 '
#245000
b1001 $
b1001 *
b1001 '
#250000
b1010 $
b1010 *
b1010 '
#255000
b1011 $
b1011 *
b1011 '
#260000
b1100 $
b1100 *
b1100 '
#265000
b1101 $
b1101 *
b1101 '
#270000
b1110 $
b1110 *
b1110 '
#275000
b1111 $
b1111 *
b1111 '
#280000
b10000 '
