lab3/comb_part1.v
module comb_part1 (
    input  wire a,
    input  wire b,
    input  wire c,
    input  wire d,
    output wire q
);
    assign q = (a | b) & (c | d);
endmodule

lab3/comb_part1_tb.v
`timescale 1ns / 1ps

module comb_part1_tb;
    reg a, b, c, d;
    wire q;

    comb_part1 dut (
        .a(a),
        .b(b),
        .c(c),
        .d(d),
        .q(q)
    );

    wire expected = (a | b) & (c | d);

    integer i;

    initial begin
        $dumpfile("comb_part1_wave_tb.vcd");
        $dumpvars(0, comb_part1_tb);

        a = 0; b = 0; c = 0; d = 0;
        repeat (2) begin
            for (i = 0; i < 16; i = i + 1) begin
                {a, b, c, d} = i[3:0];
                #5;
            end
        end

        #10 $finish;
    end

    always @* begin
        if (q !== expected) begin
            $display("Mismatch at time %0t: a=%0b b=%0b c=%0b d=%0b -> q=%0b expected=%0b",
                     $time, a, b, c, d, q, expected);
            $fatal;
        end
    end
endmodule

lab3/comb_part1_wave_tb.vcd
$date
	Tue Nov 04 14:33:23 2025
$end
$version
	Icarus Verilog
$end
$timescale
	1ps
$end
$scope module comb_part1_tb $end
$var wire 1 ! expected $end
$var wire 1 " q $end
$var reg 1 # a $end
$var reg 1 $ b $end
$var reg 1 % c $end
$var reg 1 & d $end
$var integer 32 ' i [31:0] $end
$scope module dut $end
$var wire 1 # a $end
$var wire 1 $ b $end
$var wire 1 % c $end
$var wire 1 & d $end
$var wire 1 " q $end
$upscope $end
$upscope $end
$enddefinitions $end
$comment Show the parameter values. $end
$dumpall
$end
#0
$dumpvars
b0 '
0&
0%
0$
0#
0"
0!
$end
#5000
1&
b1 '
#10000
1%
0&
b10 '
#15000
1&
b11 '
#20000
1$
0%
0&
b100 '
#25000
1"
1!
1&
b101 '
#30000
1%
0&
b110 '
#35000
1&
b111 '
#40000
0"
0!
1#
0$
0%
0&
b1000 '
#45000
1"
1!
1&
b1001 '
#50000
1%
0&
b1010 '
#55000
1&
b1011 '
#60000
0"
0!
1$
0%
0&
b1100 '
#65000
1"
1!
1&
b1101 '
#70000
1%
0&
b1110 '
#75000
1&
b1111 '
#80000
0"
0!
0#
0$
0%
0&
b0 '
#85000
1&
b1 '
#90000
1%
0&
b10 '
#95000
1&
b11 '
#100000
1$
0%
0&
b100 '
#105000
1"
1!
1&
b101 '
#110000
1%
0&
b110 '
#115000
1&
b111 '
#120000
0"
0!
1#
0$
0%
0&
b1000 '
#125000
1"
1!
1&
b1001 '
#130000
1%
0&
b1010 '
#135000
1&
b1011 '
#140000
0"
0!
1$
0%
0&
b1100 '
#145000
1"
1!
1&
b1101 '
#150000
1%
0&
b1110 '
#155000
1&
b1111 '
#160000
b10000 '
