lab3/comb_part2.v
module comb_part2 (
    input  wire a,
    input  wire b,
    input  wire c,
    input  wire d,
    output wire q
);
    assign q = b | c;
endmodule

lab3/comb_part2_tb.v
`timescale 1ns / 1ps

module comb_part2_tb;
    reg a, b, c, d;
    wire q;

    comb_part2 dut (
        .a(a),
        .b(b),
        .c(c),
        .d(d),
        .q(q)
    );

    wire expected = b | c;
    integer i;

    initial begin
        $dumpfile("comb_part2_wave_tb.vcd");
        $dumpvars(0, comb_part2_tb);

        for (i = 0; i < 16; i = i + 1) begin
            {a, b, c, d} = i[3:0];
            #10;
            if (q !== expected) begin
                $display("Mismatch at time %0t: a=%0b b=%0b c=%0b d=%0b -> q=%0b expected=%0b",
                         $time, a, b, c, d, q, expected);
                $fatal;
            end
        end
        #10 $finish;
    end
endmodule

lab3/comb_part2_wave_tb.vcd
$date
	Tue Nov 04 14:33:35 2025
$end
$version
	Icarus Verilog
$end
$timescale
	1ps
$end
$scope module comb_part2_tb $end
$var wire 1 ! expected $end
$var wire 1 " q $end
$var reg 1 # a $end
$var reg 1 $ b $end
$var reg 1 % c $end
$var reg 1 & d $end
$var integer 32 ' i [31:0] $end
$scope module dut $end
$var wire 1 # a $end
$var wire 1 $ b $end
$var wire 1 % c $end
$var wire 1 & d $end
$var wire 1 " q $end
$upscope $end
$upscope $end
$enddefinitions $end
$comment Show the parameter values. $end
$dumpall
$end
#0
$dumpvars
b0 '
0&
0%
0$
0#
0"
0!
$end
#10000
1&
b1 '
#20000
1"
1!
1%
0&
b10 '
#30000
1&
b11 '
#40000
1$
0%
0&
b100 '
#50000
1&
b101 '
#60000
1%
0&
b110 '
#70000
1&
b111 '
#80000
0"
0!
1#
0$
0%
0&
b1000 '
#90000
1&
b1001 '
#100000
1"
1!
1%
0&
b1010 '
#110000
1&
b1011 '
#120000
1$
0%
0&
b1100 '
#130000
1&
b1101 '
#140000
1%
0&
b1110 '
#150000
1&
b1111 '
#160000
b10000 '
