lab3/seq_part6.v
module seq_part6 (
    input  wire clk,
    input  wire a,
    input  wire b,
    output reg  q,
    output reg  state
);
    initial begin
        state = 1'b0;
        q     = 1'b0;
    end

    always @(posedge clk) begin
        q <= state ? b : a;
        state <= (state ? a : b);
    end
endmodule

lab3/seq_part6_tb.v
`timescale 1ns / 1ps

module seq_part6_tb;
    reg clk;
    reg a;
    reg b;
    wire q;
    wire state;

    seq_part6 dut (
        .clk(clk),
        .a(a),
        .b(b),
        .q(q),
        .state(state)
    );

    reg expected_state;
    reg expected_q;

    initial begin
        clk = 0;
        forever #5 clk = ~clk;
    end

    initial begin
        $dumpfile("seq_part6_wave_tb.vcd");
        $dumpvars(0, seq_part6_tb);

        a = 0;
        b = 0;
        expected_state = 0;
        expected_q = 0;

        #45 a = 1;
        #20 b = 1;
        #15 b = 0;
        #20 a = 0;
        #20 a = 1;
        #20 a = 0;
        #15 b = 1;
        #20 b = 0;
        #10 $finish;
    end

    always @(posedge clk) begin
        expected_q     <= expected_state ? b : a;
        expected_state <= expected_state ? a : b;

        if (q !== expected_q) begin
            $display("Mismatch q at time %0t: a=%0b b=%0b q=%0b expected=%0b",
                     $time, a, b, q, expected_q);
            $fatal;
        end
        if (state !== expected_state) begin
            $display("Mismatch state at time %0t: a=%0b b=%0b state=%0b expected=%0b",
                     $time, a, b, state, expected_state);
            $fatal;
        end
    end
endmodule

lab3/seq_part6_wave_tb.vcd
$date
	Tue Nov 04 14:36:05 2025
$end
$version
	Icarus Verilog
$end
$timescale
	1ps
$end
$scope module seq_part6_tb $end
$var wire 1 ! state $end
$var wire 1 " q $end
$var reg 1 # a $end
$var reg 1 $ b $end
$var reg 1 % clk $end
$var reg 1 & expected_q $end
$var reg 1 ' expected_state $end
$scope module dut $end
$var wire 1 # a $end
$var wire 1 $ b $end
$var wire 1 % clk $end
$var reg 1 " q $end
$var reg 1 ! state $end
$upscope $end
$upscope $end
$enddefinitions $end
$comment Show the parameter values. $end
$dumpall
$end
#0
$dumpvars
0'
0&
0%
0$
0#
0"
0!
$end
#5000
1%
#10000
0%
#15000
1%
#20000
0%
#25000
1%
#30000
0%
#35000
1%
#40000
0%
#45000
1"
1&
1%
1#
#50000
0%
#55000
1%
#60000
0%
#65000
1!
1'
1%
1$
#70000
0%
#75000
1%
#80000
0%
0$
#85000
0"
0&
1%
#90000
0%
#95000
1%
#100000
0%
0#
#105000
0!
0'
1%
#110000
0%
#115000
1%
#120000
0%
1#
#125000
1"
1&
1%
#130000
0%
#135000
1%
#140000
0%
0#
#145000
0"
0&
1%
#150000
0%
#155000
1'
1!
1%
1$
#160000
0%
#165000
0!
1"
0'
1&
1%
#170000
0%
#175000
0&
0"
1%
0$
