lab3/seq_part5.v
module seq_part5 (
    input  wire       clk,
    input  wire       a,
    output reg [3:0]  q
);
    initial q = 4'd4;

    always @(posedge clk) begin
        if (a) begin
            q <= 4'd4;
        end else begin
            if (q == 4'd6) begin
                q <= 4'd0;
            end else begin
                q <= q + 4'd1;
            end
        end
    end
endmodule

lab3/seq_part5_tb.v
`timescale 1ns / 1ps

module seq_part5_tb;
    reg clk;
    reg a;
    wire [3:0] q;

    seq_part5 dut (
        .clk(clk),
        .a(a),
        .q(q)
    );

    reg [3:0] expected;

    initial begin
        clk = 0;
        forever #5 clk = ~clk;
    end

    initial begin
        $dumpfile("seq_part5_wave_tb.vcd");
        $dumpvars(0, seq_part5_tb);

        a = 1'b1;
        expected = 4'd4;

        #40 a = 1'b0;
        #120 a = 1'b1;
        #40 a = 1'b0;

        #80 $finish;
    end

    always @(posedge clk) begin
        if (a) begin
            expected <= 4'd4;
        end else begin
            if (expected == 4'd6) begin
                expected <= 4'd0;
            end else begin
                expected <= expected + 4'd1;
            end
        end

        if (q !== expected) begin
            $display("Mismatch at time %0t: a=%0b q=%0d expected=%0d", $time, a, q, expected);
            $fatal;
        end
    end
endmodule

lab3/seq_part5_wave_tb.vcd
$date
	Tue Nov 04 14:35:26 2025
$end
$version
	Icarus Verilog
$end
$timescale
	1ps
$end
$scope module seq_part5_tb $end
$var wire 4 ! q [3:0] $end
$var reg 1 " a $end
$var reg 1 # clk $end
$var reg 4 $ expected [3:0] $end
$scope module dut $end
$var wire 1 " a $end
$var wire 1 # clk $end
$var reg 4 % q [3:0] $end
$upscope $end
$upscope $end
$enddefinitions $end
$comment Show the parameter values. $end
$dumpall
$end
#0
$dumpvars
b100 %
b100 $
0#
1"
b100 !
$end
#5000
1#
#10000
0#
#15000
1#
#20000
0#
#25000
1#
#30000
0#
#35000
1#
#40000
0#
0"
#45000
b101 !
b101 %
b101 $
1#
#50000
0#
#55000
b110 $
b110 !
b110 %
1#
#60000
0#
#65000
b0 !
b0 %
b0 $
1#
#70000
0#
#75000
b1 $
b1 !
b1 %
1#
#80000
0#
#85000
b10 !
b10 %
b10 $
1#
#90000
0#
#95000
b11 $
b11 !
b11 %
1#
#100000
0#
#105000
b100 !
b100 %
b100 $
1#
#110000
0#
#115000
b101 $
b101 !
b101 %
1#
#120000
0#
#125000
b110 !
b110 %
b110 $
1#
#130000
0#
#135000
b0 $
b0 !
b0 %
1#
#140000
0#
#145000
b1 !
b1 %
b1 $
1#
#150000
0#
#155000
b10 $
b10 !
b10 %
1#
#160000
0#
1"
#165000
b100 !
b100 %
b100 $
1#
#170000
0#
#175000
1#
#180000
0#
#185000
1#
#190000
0#
#195000
1#
#200000
0#
0"
#205000
b101 !
b101 %
b101 $
1#
#210000
0#
#215000
b110 $
b110 !
b110 %
1#
#220000
0#
#225000
b0 !
b0 %
b0 $
1#
#230000
0#
#235000
b1 $
b1 !
b1 %
1#
#240000
0#
#245000
b10 !
b10 %
b10 $
1#
#250000
0#
#255000
b11 $
b11 !
b11 %
1#
#260000
0#
#265000
b100 !
b100 %
b100 $
1#
#270000
0#
#275000
b101 $
b101 !
b101 %
1#
