lab3/seq_part4.v
module seq_part4 (
    input  wire clk,
    input  wire a,
    output reg  p,
    output reg  q
);
    initial begin
        p = 1'b0;
        q = 1'b0;
    end

    always @(posedge clk) begin
        p <= a;
        q <= p;
    end
endmodule

lab3/seq_part4_tb.v
`timescale 1ns / 1ps

module seq_part4_tb;
    reg clk;
    reg a;
    wire p, q;

    seq_part4 dut (
        .clk(clk),
        .a(a),
        .p(p),
        .q(q)
    );

    reg expected_p, expected_q;

    initial begin
        clk = 0;
        forever #5 clk = ~clk;
    end

    initial begin
        a = 0;
        expected_p = 0;
        expected_q = 0;

        $dumpfile("seq_part4_wave_tb.vcd");
        $dumpvars(0, seq_part4_tb);

        #12 a = 1;
        #15 a = 0;
        #10 a = 1;
        #10 a = 0;
        #20 a = 1;
        #15 a = 0;
        #25 a = 1;
        #20 a = 0;

        #30 $finish;
    end

    always @(posedge clk) begin
        expected_p <= a;
        expected_q <= expected_p;
        if (p !== expected_p) begin
            $display("Mismatch p at time %0t: a=%0b p=%0b expected=%0b", $time, a, p, expected_p);
            $fatal;
        end
        if (q !== expected_q) begin
            $display("Mismatch q at time %0t: a=%0b q=%0b expected=%0b", $time, a, q, expected_q);
            $fatal;
        end
    end
endmodule

lab3/seq_part4_wave_tb.vcd
$date
	Tue Nov 04 14:34:53 2025
$end
$version
	Icarus Verilog
$end
$timescale
	1ps
$end
$scope module seq_part4_tb $end
$var wire 1 ! q $end
$var wire 1 " p $end
$var reg 1 # a $end
$var reg 1 $ clk $end
$var reg 1 % expected_p $end
$var reg 1 & expected_q $end
$scope module dut $end
$var wire 1 # a $end
$var wire 1 $ clk $end
$var reg 1 " p $end
$var reg 1 ! q $end
$upscope $end
$upscope $end
$enddefinitions $end
$comment Show the parameter values. $end
$dumpall
$end
#0
$dumpvars
0&
0%
0$
0#
0"
0!
$end
#5000
1$
#10000
0$
#12000
1#
#15000
1%
1"
1$
#20000
0$
#25000
1!
1&
1$
#27000
0#
#30000
0$
#35000
0%
0"
1$
#37000
1#
#40000
0$
#45000
0!
1"
0&
1%
1$
#47000
0#
#50000
0$
#55000
1&
0%
1!
0"
1$
#60000
0$
#65000
0!
0&
1$
#67000
1#
#70000
0$
#75000
1%
1"
1$
#80000
0$
#82000
0#
#85000
1!
0"
1&
0%
1$
#90000
0$
#95000
0&
0!
1$
#100000
0$
#105000
1$
#107000
1#
#110000
0$
#115000
1%
1"
1$
#120000
0$
#125000
1!
1&
1$
#127000
0#
#130000
0$
#135000
0%
0"
1$
#140000
0$
#145000
0!
0&
1$
