lab3/timer_part2.v
module timer_part2 (
    input  wire      clk,
    input  wire      shift_ena,
    input  wire      count_ena,
    input  wire      data,
    output reg [3:0] q
);
    initial q = 4'd0;

    always @(posedge clk) begin
        if (shift_ena) begin
            q <= {q[2:0], data};
        end else if (count_ena) begin
            q <= q - 4'd1;
        end
    end
endmodule

lab3/timer_part2_tb.v
`timescale 1ns / 1ps

module timer_part2_tb;
    reg clk;
    reg shift_ena;
    reg count_ena;
    reg data;
    wire [3:0] q;

    timer_part2 dut (
        .clk(clk),
        .shift_ena(shift_ena),
        .count_ena(count_ena),
        .data(data),
        .q(q)
    );

    reg [3:0] expected;
    integer i;

    initial begin
        clk = 0;
        forever #5 clk = ~clk;
    end

    task automatic shift_in(input [3:0] value);
        reg [3:0] next_expected;
        begin
            shift_ena = 1'b1;
            for (i = 3; i >= 0; i = i - 1) begin
                data = (value >> i) & 1'b1;
                next_expected = {expected[2:0], data};
                @(posedge clk);
                #1;
                if (q !== next_expected) begin
                    $display("Shift mismatch at time %0t: data=%0b q=%0h expected=%0h",
                             $time, data, q, next_expected);
                    $fatal;
                end
                expected = next_expected;
            end
            shift_ena = 1'b0;
            data = 1'b0;
        end
    endtask

    task automatic count_down(input integer steps);
        reg [3:0] next_expected;
        integer k;
        begin
            for (k = 0; k < steps; k = k + 1) begin
                count_ena = 1'b1;
                next_expected = expected - 4'd1;
                @(posedge clk);
                #1;
                if (q !== next_expected) begin
                    $display("Count mismatch at time %0t: q=%0h expected=%0h",
                             $time, q, next_expected);
                    $fatal;
                end
                expected = next_expected;
                count_ena = 1'b0;
                @(negedge clk);
            end
        end
    endtask

    initial begin
        $dumpfile("timer_part2_wave_tb.vcd");
        $dumpvars(0, timer_part2_tb);

        shift_ena = 0;
        count_ena = 0;
        data = 0;
        expected = 4'd0;

        repeat (2) @(posedge clk);

        shift_in(4'h9);
        repeat (2) @(posedge clk);

        count_down(5);
        repeat (2) @(posedge clk);

        shift_in(4'h4);
        repeat (2) @(posedge clk);

        count_down(3);

        #20 $finish;
    end
endmodule

lab3/timer_part2_wave_tb.vcd
$date
	Tue Nov 04 14:45:42 2025
$end
$version
	Icarus Verilog
$end
$timescale
	1ps
$end
$scope module timer_part2_tb $end
$var wire 4 ! q [3:0] $end
$var reg 1 " clk $end
$var reg 1 # count_ena $end
$var reg 1 $ data $end
$var reg 4 % expected [3:0] $end
$var reg 1 & shift_ena $end
$var integer 32 ' i [31:0] $end
$scope module dut $end
$var wire 1 " clk $end
$var wire 1 # count_ena $end
$var wire 1 $ data $end
$var wire 1 & shift_ena $end
$var reg 4 ( q [3:0] $end
$upscope $end
$scope task count_down $end
$upscope $end
$scope task shift_in $end
$upscope $end
$upscope $end
$enddefinitions $end
$comment Show the parameter values. $end
$dumpall
$end
#0
$dumpvars
b0 (
bx '
0&
b0 %
0$
0#
0"
b0 !
$end
#5000
1"
#10000
0"
#15000
1$
b11 '
1&
1"
#20000
0"
#25000
b1 !
b1 (
1"
#26000
0$
b10 '
b1 %
#30000
0"
#35000
b10 !
b10 (
1"
#36000
b1 '
b10 %
#40000
0"
#45000
b100 !
b100 (
1"
#46000
1$
b0 '
b100 %
#50000
0"
#55000
b1001 !
b1001 (
1"
#56000
0$
0&
b11111111111111111111111111111111 '
b1001 %
#60000
0"
#65000
1"
#70000
0"
#75000
1#
1"
#80000
0"
#85000
b1000 !
b1000 (
1"
#86000
0#
b1000 %
#90000
1#
0"
#95000
b111 !
b111 (
1"
#96000
0#
b111 %
#100000
1#
0"
#105000
b110 !
b110 (
1"
#106000
0#
b110 %
#110000
1#
0"
#115000
b101 !
b101 (
1"
#116000
0#
b101 %
#120000
1#
0"
#125000
b100 !
b100 (
1"
#126000
0#
b100 %
#130000
0"
#135000
1"
#140000
0"
#145000
b11 '
1&
1"
#150000
0"
#155000
b1000 !
b1000 (
1"
#156000
1$
b10 '
b1000 %
#160000
0"
#165000
b1 !
b1 (
1"
#166000
0$
b1 '
b1 %
#170000
0"
#175000
b10 !
b10 (
1"
#176000
b0 '
b10 %
#180000
0"
#185000
b100 !
b100 (
1"
#186000
0&
b11111111111111111111111111111111 '
b100 %
#190000
0"
#195000
1"
#200000
0"
#205000
1#
1"
#210000
0"
#215000
b11 !
b11 (
1"
#216000
0#
b11 %
#220000
1#
0"
#225000
b10 !
b10 (
1"
#226000
0#
b10 %
#230000
1#
0"
#235000
b1 !
b1 (
1"
#236000
0#
b1 %
