lab3/timer_part3.v
module timer_part3 (
    input  wire clk,
    input  wire reset,
    input  wire data,
    output reg  start_shifting
);
    localparam STATE_IDLE    = 2'd0;
    localparam STATE_HAVE_1  = 2'd1;
    localparam STATE_HAVE_11 = 2'd2;
    localparam STATE_HAVE_110 = 2'd3;

    reg [1:0] state;

    initial begin
        state = STATE_IDLE;
        start_shifting = 1'b0;
    end

    always @(posedge clk) begin
        if (reset) begin
            state <= STATE_IDLE;
            start_shifting <= 1'b0;
        end else begin
            start_shifting <= 1'b0;
            case (state)
                STATE_IDLE: begin
                    if (data) begin
                        state <= STATE_HAVE_1;
                    end
                end
                STATE_HAVE_1: begin
                    if (data) begin
                        state <= STATE_HAVE_11;
                    end else begin
                        state <= STATE_IDLE;
                    end
                end
                STATE_HAVE_11: begin
                    if (data) begin
                        state <= STATE_HAVE_11;
                    end else begin
                        state <= STATE_HAVE_110;
                    end
                end
                STATE_HAVE_110: begin
                    if (data) begin
                        start_shifting <= 1'b1;
                        state <= STATE_HAVE_1;
                    end else begin
                        state <= STATE_IDLE;
                    end
                end
                default: begin
                    state <= STATE_IDLE;
                end
            endcase
        end
    end
endmodule

lab3/timer_part3_tb.v
`timescale 1ns / 1ps

module timer_part3_tb;
    reg clk;
    reg reset;
    reg data;
    wire start_shifting;

    timer_part3 dut (
        .clk(clk),
        .reset(reset),
        .data(data),
        .start_shifting(start_shifting)
    );

    reg [3:0] history;
    integer pulse_count;

    initial begin
        clk = 1'b0;
        forever #5 clk = ~clk;
    end

    task automatic drive_bit(input reg value);
        reg [3:0] next_history;
        reg       expected;
        begin
            data = value;
            @(posedge clk);
            next_history = {history[2:0], value};
            if (reset) begin
                history = 4'b0000;
                expected = 1'b0;
            end else begin
                expected = (next_history == 4'b1101);
                history = next_history;
            end
            #1;
            if (start_shifting !== expected) begin
                $display("Mismatch at time %0t: data=%0b expected pulse=%0b got=%0b history=%0b",
                         $time, value, expected, start_shifting, next_history);
                $fatal;
            end
            if (start_shifting) begin
                pulse_count = pulse_count + 1;
            end
        end
    endtask

    initial begin
        $dumpfile("timer_part3_wave_tb.vcd");
        $dumpvars(0, timer_part3_tb);

        history = 4'b0000;
        pulse_count = 0;

        reset = 1'b1;
        data = 1'b0;

        repeat (3) @(posedge clk);
        reset = 1'b0;

        drive_bit(1'b1);
        drive_bit(1'b1);
        drive_bit(1'b0);
        drive_bit(1'b1);

        drive_bit(1'b1);
        drive_bit(1'b0);
        drive_bit(1'b1);
        drive_bit(1'b0);
        drive_bit(1'b1);
        drive_bit(1'b1);
        drive_bit(1'b0);
        drive_bit(1'b0);
        drive_bit(1'b1);

        reset = 1'b1;
        @(posedge clk);
        reset = 1'b0;
        history = 4'b0000;

        drive_bit(1'b1);
        drive_bit(1'b1);
        drive_bit(1'b0);
        drive_bit(1'b1);
        drive_bit(1'b1);
        drive_bit(1'b0);

        if (pulse_count !== 3) begin
            $display("Unexpected number of pulses: %0d", pulse_count);
            $fatal;
        end

        #20;
        $display("timer_part3_tb completed successfully");
        $finish;
    end
endmodule

lab3/timer_part3_wave_tb.vcd
$date
	Wed Nov 05 18:15:06 2025
$end
$version
	Icarus Verilog
$end
$timescale
	1ps
$end
$scope module timer_part3_tb $end
$var wire 1 ! start_shifting $end
$var reg 1 " clk $end
$var reg 1 # data $end
$var reg 4 $ history [3:0] $end
$var reg 1 % reset $end
$var integer 32 & pulse_count [31:0] $end
$scope module dut $end
$var wire 1 " clk $end
$var wire 1 # data $end
$var wire 1 % reset $end
$var parameter 2 ' STATE_HAVE_1 $end
$var parameter 2 ( STATE_HAVE_11 $end
$var parameter 2 ) STATE_HAVE_110 $end
$var parameter 2 * STATE_IDLE $end
$var reg 1 ! start_shifting $end
$var reg 2 + state [1:0] $end
$upscope $end
$scope task drive_bit $end
$upscope $end
$upscope $end
$enddefinitions $end
$comment Show the parameter values. $end
$dumpall
b0 *
b11 )
b10 (
b1 '
$end
#0
$dumpvars
b0 +
b0 &
1%
b0 $
0#
0"
0!
$end
#5000
1"
#10000
0"
#15000
1"
#20000
0"
#25000
1#
0%
1"
#30000
0"
#35000
b1 +
b1 $
1"
#40000
0"
#45000
b10 +
b11 $
1"
#46000
0#
#50000
0"
#55000
b11 +
b110 $
1"
#56000
1#
#60000
0"
#65000
b1 +
1!
b1101 $
1"
#66000
b1 &
#70000
0"
#75000
b10 +
0!
b1011 $
1"
#76000
0#
#80000
0"
#85000
b11 +
b110 $
1"
#86000
1#
#90000
0"
#95000
b1 +
1!
b1101 $
1"
#96000
0#
b10 &
#100000
0"
#105000
b0 +
0!
b1010 $
1"
#106000
1#
#110000
0"
#115000
b1 +
b101 $
1"
#120000
0"
#125000
b10 +
b1011 $
1"
#126000
0#
#130000
0"
#135000
b11 +
b110 $
1"
#140000
0"
#145000
b0 +
b1100 $
1"
#146000
1#
#150000
0"
#155000
b1 +
b1001 $
1"
#156000
1%
#160000
0"
#165000
b10 +
b0 $
0%
1"
#170000
0"
#175000
b1 $
1"
#180000
0"
#185000
b11 $
1"
#186000
0#
#190000
0"
#195000
b11 +
b110 $
1"
#196000
1#
#200000
0"
#205000
b1 +
1!
b1101 $
1"
#206000
b11 &
#210000
0"
#215000
b10 +
0!
b1011 $
1"
#216000
0#
#220000
0"
#225000
b11 +
b110 $
1"
#230000
0"
#235000
b0 +
1"
